flake8_cached2/.__main__.py.un~
flake8_cached2/.cli.py.un~
flake8_cached2/__init__.py
flake8_cached2/__main__.py
flake8_cached2/cacher.py
flake8_cached2/cli.py
flake8_cached2-0.0.3.dist-info/entry_points.txt
flake8_cached2-0.0.3.dist-info/LICENSE.md
flake8_cached2-0.0.3.dist-info/WHEEL
flake8_cached2-0.0.3.dist-info/METADATA
flake8_cached2-0.0.3.dist-info/RECORD
