Metadata-Version: 2.1
Name: flake8-cached2
Version: 0.0.3
Summary: A wrapper around flake8's cli that uses cache at file level
Home-page: https://pypi.org/project/flake8-cached
License: MIT
Keywords: flake8
Author: Noortheen Raja 
Author-email: jnoortheen@gmail.com
Requires-Python: >=3.8,<4.0
Classifier: Development Status :: 1 - Planning
Classifier: License :: OSI Approved :: MIT License
Classifier: Natural Language :: English
Classifier: Operating System :: OS Independent
Classifier: Programming Language :: Python
Classifier: Programming Language :: Python :: 3
Classifier: Programming Language :: Python :: 3.10
Classifier: Programming Language :: Python :: 3.6
Classifier: Programming Language :: Python :: 3.8
Classifier: Programming Language :: Python :: 3.9
Requires-Dist: flake8 (>=3.9.0)
Project-URL: Repository, https://github.com/jnoortheen/flake8-cached
